request_casting/__init__.py
request_casting/locale/en/LC_MESSAGES/request_casting.mo
request_casting/locale/en.po
request_casting/locale/es/LC_MESSAGES/request_casting.mo
request_casting/locale/es.po
request_casting/locale/request_casting.pot
request_casting/poethepoet.py
request_casting/request_casting.py
request_casting-0.7.0.dist-info/LICENSE
request_casting-0.7.0.dist-info/METADATA
request_casting-0.7.0.dist-info/WHEEL
request_casting-0.7.0.dist-info/RECORD
