Metadata-Version: 2.1
Name: request_casting
Version: 0.7.0
Summary: Provide method to cast django request data for POST and GET methods
License: GPL-3.0 license
Author: turulomio
Author-email: turulomio@yahoo.es
Requires-Python: >3.10,<4.0
Classifier: License :: Other/Proprietary License
Classifier: Programming Language :: Python :: 3
Classifier: Programming Language :: Python :: 3.11
Classifier: Programming Language :: Python :: 3.12
Requires-Dist: pydicts (>=0.16.0)
